[
  {
    "iso": "KEN",
    "country": "肯亞",
    "introduction": "東非和中非經濟領頭羊，觀光業和手機通訊業近年快速發展，首都奈洛比更是東非的金融中心。",
    "symbol": "Telecommunications(手機通訊)",
    "currency": "肯亞先令",
    "language": "英語(Officail)、斯瓦希里語(Swahili)",
    "flag": "kenya_flag.png",
    "emblem": "kenya_svg.png",
    "headOfState": "總統: Uhuru Kenyataa",
    "politics": "總統制",
    "atmosphere": "從東邊肯亞山附近較涼爽乾燥氣候，到西南邊境，維多利亞大湖區的炎熱、潮濕氣候。",
    "geography": "東部海岸平原區+南部大裂谷+中部大裂谷及其高原區域+平坦高原上的維多利亞湖盆區",
    "capital": "Nairobi 奈洛比",
    "population": "45 Million",
    "faith": [{
        "name": "天主/基督新教",
        "percentage": 83
      }, {
        "name": "伊斯蘭教",
        "percentage": 11.2
      }, {
        "name": "印度教",
        "percentage": 1.7
      }, {
        "name": "其他",
        "percentage": 4.1
      }
    ],
    "economy": [{
        "name": "一級產業-茶",
        "percentage": 24.2
      }, {
        "name": "二級產業-消費產品製造",
        "percentage": 14.8
      }, {
        "name": "三級產業-觀光、金融",
        "percentage": 61.0
      }
    ]
  },
  {
    "iso": "TZA",
    "country": "坦尚尼亞 Tanzania",
    "introduction": "以和平為人所著稱。曾受英國殖民的它，在去年時決定不再使用英語為教學語言，而是當地語言－斯瓦希里語。",
    "symbol": "野生動物國家公園 (Wildlife)",
    "currency": "坦尚尼亞先令",
    "language": "英語、斯瓦希里語(Swahili)",
    "flag": "Tanzania_flag.png",
    "emblem": "Tanzania_flag.png",
    "headOfState": "總統: Jakaya Kikwete 總理: Mizengo Pinda",
    "politics": "雙首長制",
    "atmosphere": "東部的熱帶草原氣候，西部內陸高原則屬熱帶高地氣候。整體來說氣溫平均為21—25℃，乾濕季分明。",
    "geography": "東瀕印度洋，為沿海平原地區+內陸低地區域+西部的高原地區。非洲最高峰－吉力馬札羅山，位於坦尚尼亞東北部。",
    "capital": "Dodoma 杜篤瑪",
    "population": "43 Million",
    "faith": [{
        "name": "天主/基督新教",
        "percentage": 35
      }, {
        "name": "斯蘭教",
        "percentage": 45
      }, {
        "name": "原始拜物教",
        "percentage": 20
      }
    ],
    "economy": [{
        "name": "一級產業-糧食作物: 玉米；經濟作物: 糖；畜牧業: 牛肉",
        "percentage": 24.5
      }, {
        "name": "二級產業-物加工製造與營造業",
        "percentage": 22.2
      }, {
        "name": "三級產業-觀光、金融",
        "percentage": 53.3
      }
    ]
  },
  {
    "iso": "DZA",
    "country": "阿爾及利亞 Algeria",
    "introduction": "阿爾及利亞是瀕臨地中海的國家中，國土面積最大的，也是在非洲國家中，占地第二大。阿拉伯文明為主要文化，阿爾及利亞人民解放陣線是主要政黨。",
    "symbol": "礦產資源: 天然氣(Natural gas)",
    "currency": "阿爾及利亞第納爾(Dinar)",
    "language": "阿拉伯語",
    "flag": "Algeria_flag.png",
    "emblem": "Algeria_seal.png",
    "headOfState": "總統: Abdelaziz Bouteflika 總理: Abdelmalek Sellal",
    "politics": "半總統制",
    "atmosphere": "北部較溫和濕潤，屬地中海氣候；中南部的高地區譽為過渡性氣候；南部沙漠地帶，氣候乾熱，屬熱帶沙漠氣候。",
    "geography": "北部沿海平原和阿特拉斯山脈+中南部是撒哈拉阿特拉斯山脈和大高原+最南部則涉及撒哈拉沙漠的西北區域。",
    "capital": "阿爾及爾 Algiers",
    "population": "37.9 Million(2013)",
    "faith": [{
        "name": "遜尼派穆斯林Sunni Muslim",
        "percentage": 99
      }, {
        "name": "基督教和猶太教",
        "percentage": 1
      }
    ],
    "economy": [{
        "name": "一級產業-地中海作物",
        "percentage": 9.4
      }, {
        "name": "二級產業-石油、天然氣，食品加工",
        "percentage": 62.6
      }, {
        "name": "三級產業",
        "percentage": 28
      }
    ]
  },
  {
    "iso": "EGY",
    "country": "埃及 Eygypt",
    "introduction": "埃及為世界古文明國之一，被視為中等強國，經濟發展均衡。然而，人口分布過於集中一直是埃及所頭痛的問題，找到解決方法是埃及的重要目標。",
    "symbol": "金字塔",
    "currency": "埃及鎊",
    "language": "阿拉伯語",
    "flag": "Egypt_flag.png",
    "emblem": "Egypt_seal.png",
    "headOfState": "總統: Abdel Fattah el-Sisi 總理: Ibrahim Mahlab",
    "politics": "半總統制",
    "atmosphere": "全境乾燥少雨。尼羅河三角洲和北部沿海地區屬地中海型氣候，其餘大部分地區屬熱帶沙漠氣候，炎熱乾燥。",
    "geography": "除尼羅河谷及開羅以下的三角洲 ，為狹窄綠帶，其餘地區為沙漠，而東北部的西奈半島則為一片多山的高原。",
    "capital": "開羅 Cairo",
    "population": "86 Million(2014)",
    "faith": [{
        "name": "伊斯蘭教",
        "percentage": 90
      }, {
        "name": "其他",
        "percentage": 10
      }
    ],
    "economy": [{
        "name": "一級產業-棉花",
        "percentage": 14.5
      }, {
        "name": "二級產業-石油採礦業",
        "percentage": 47.5
      }, {
        "name": "三級產業-旅遊業、勞務出口",
        "percentage": 48
      }
    ]
  },
  {
    "iso": "MAR",
    "country": "摩洛哥 Morocco",
    "introduction": "摩洛哥常年氣候宜人、花草繁盛，有\"北非後花園\"之稱，旅遊業是其重要的外匯來源之一。從古至今，摩洛哥一直是非洲和歐洲之間的交通要道。",
    "symbol": "露天市場(souk)",
    "currency": "摩洛哥迪拉姆",
    "language": "阿拉伯語",
    "flag": "Morocco_flag.png",
    "emblem": "Morocco_seal.png",
    "headOfState": "國王: Mohammed VI 總理: Abdelilah Benkirane",
    "politics": "君主立憲制",
    "atmosphere": "因處於副熱帶高壓帶和加那利寒流影響下，形成乾燥的熱帶沙漠氣候；而斜貫全國的阿特拉斯山阻擋了南部撒哈拉沙漠熱浪的侵襲。",
    "geography": "位於交通要塞，是地中海入大西洋的門戶。中部和北部為山脈地形，東部和南部是上高原和前撒哈拉高原，西北沿海一帶為狹長的平原。",
    "capital": "拉巴特 Rabat",
    "population": "32.5 Million(2012)",
    "faith": [{
        "name": "伊斯蘭教",
        "percentage": 99
      }, {
        "name": "基督教",
        "percentage": 1
      }
    ],
    "economy": [{
        "name": "一級產業-漁業",
        "percentage": 15.1
      }, {
        "name": "二級產業-磷酸礦業",
        "percentage": 31.7
      }, {
        "name": "三級產業-旅遊業",
        "percentage": 53.2
      }
    ]
  },
  {
    "iso": "UGA",
    "country": "烏干達 Uganda",
    "introduction": "烏干達得天獨厚，擁有壯麗的地形和宜人的氣候，有\"非洲明珠\"之稱。而境內因英國殖民政府強行劃分土地，而有非常多元的種族、行政系統和文化。",
    "symbol": "Boda boda(摩托計程車)",
    "currency": "烏干達先令",
    "language": "英語、斯瓦希里語(Swahili)",
    "flag": "Uganda_flag.png",
    "emblem": "Uganda_Coat_of_arms.png",
    "headOfState": "總統: Yoweri Museveni 總理: Ruhakana Rugunda",
    "politics": "總統制",
    "atmosphere": "東北是酷熱乾燥的沙漠，西部是雨量豐富的森林區。境內山水相間，氣溫宜人，雨量豐富，大部份地區的氣候終年有如舒適的歐洲夏季。",
    "geography": "瀕臨大湖的內陸國家，整個國家坐落於高原之上，同時位於東非地塹區，東西兩邊都有高山，境內山高谷深。",
    "capital": "坎培拉 Kampala ",
    "population": "36.8 Million(2013)",
    "faith": [{
        "name": "羅馬天主教",
        "percentage": 41.9
      }, {
        "name": "基督新教",
        "percentage": 42
      }, {
        "name": "伊斯蘭教",
        "percentage": 12.1
      }, {
        "name": "其他",
        "percentage": 4
      }
    ],
    "economy": [{
        "name": "一級產業-咖啡、皮毛、漁業",
        "percentage": 21.8
      }, {
        "name": "二級產業-礦業、基礎製造業",
        "percentage": 26.1
      }, {
        "name": "三級產業",
        "percentage": 52.1
      }
    ]
  },
  {
    "iso": "RWA",
    "country": "盧安達 Rwanda",
    "introduction": "盧安達國立在1994年的大屠殺期間受到重創，不過此後已有所復甦。尤其靠著自給農業、快速成長的旅遊業來賺取外匯，經濟漸趨穩定。",
    "symbol": "巨猩猩 (gorillas)",
    "currency": "盧安達法郎(RWF)",
    "language": "盧安達語 法語 英語",
    "flag": "Rwanda_flag.png",
    "emblem": "Rwanda_seal.png",
    "headOfState": "總統: Paul Kagame 總理: Anastase Murekezi",
    "politics": "半總統制、共和制",
    "atmosphere": "溫帶和熱帶高原氣候，由於海拔較高，其氣溫比典型的赤道國家要低；乾濕季分明，西部和西北部降水較東部和東南部為多。",
    "geography": "盧安達整體地勢高聳，中西部以山區為主，中部為連綿起伏的丘陵，東部邊境地區則由熱帶草原、平原和沼澤組成。",
    "capital": "吉佳利 Kigali",
    "population": "12 Million (2012)",
    "faith": [{
        "name": "羅馬天主教",
        "percentage": 49.5
      }, {
        "name": "基督新教",
        "percentage": 39.4
      }, {
        "name": "天主教",
        "percentage": 4.5
      }, {
        "name": "伊斯蘭教",
        "percentage": 1.8
      }, {
        "name": "其他",
        "percentage": 4.8
      }
    ],
    "economy": [{
        "name": "一級產業-咖啡、茶",
        "percentage": 32.5
      }, {
        "name": "二級產業-日常用品製造業、採礦業",
        "percentage": 14.8
      }, {
        "name": "三級產業-金融、批發零售、旅遊業",
        "percentage": 52.7
      }
    ]
  },
  {
    "iso": "BDI",
    "country": "蒲隆地 Burundi",
    "introduction": "東非五國之一的內陸國家，而西南部瀕臨大湖。民主制度剛剛起步，國內因胡圖族(85%)與圖西族(14%)的糾葛，紛擾已久，如今，準備從12年的內戰從重新出發。",
    "symbol": "城市沙灘 (Urban Beach)",
    "currency": "蒲隆地法郎(Burundian Franc)",
    "language": "法語、克倫地語(Kirundi)",
    "flag": "Burundi_flag.png",
    "emblem": "Burundi_emblem.png",
    "headOfState": "總統: Pierre Nkurunziza",
    "politics": "總統制",
    "atmosphere": "熱帶草原氣候為主，境內雨量充沛，而整體氣候受高地調節，氣侯不算炎熱。",
    "geography": "位於東非大裂谷之上，境內地形高聳複雜，陡峭山脊是非洲兩大河流尼羅河水系與剛果河水系的分水嶺，有\"非洲之心\"之稱。",
    "capital": "布松布拉 Bujumbura",
    "population": "8.4 Million (2013)",
    "faith": [{
        "name": "天主教",
        "percentage": 62.1
      }, {
        "name": "基督教",
        "percentage": 23.9
      }, {
        "name": "伊斯蘭教",
        "percentage": 2.5
      }, {
        "name": "其他",
        "percentage": 11.5
      }
    ],
    "economy": [{
        "name": "一級產業-咖啡、茶、香蕉",
        "percentage": 34.4
      }, {
        "name": "二級產業-食品加工、啤酒及水泥製造",
        "percentage": 18.4
      }, {
        "name": "三級產業",
        "percentage": 47.2
      }
    ]
  },
  {
    "iso": "ETH",
    "country": "衣索比亞 Ethiopia",
    "introduction": "衣索比亞為世界上最古老的國家之一，也是非洲國家中人口密度最高的國家。非洲聯盟的總部位於衣索比亞的首都－阿迪斯阿貝巴，時尚盛事也常在此舉辦。",
    "symbol": "長跑選手 (Marathon runners)",
    "currency": "衣索比亞比爾(Birr)",
    "language": "阿姆哈拉語(Amharic)",
    "flag": "Ethiopia_flag.png",
    "emblem": "Ethiopia_svg.png",
    "headOfState": "總統: Mulatu Teshome 總理: Hailemariam Desalegn",
    "politics": "議會制",
    "atmosphere": "熱帶草原氣候和亞熱帶森林氣候為主，兼有山地和熱帶沙漠氣候；年降水量從西南向東北遞減。",
    "geography": "2/3國土為衣索比亞高原，有\"非洲屋脊\"之稱；東南屬索馬利亞高地；東非大裂谷縱貫全境中部。",
    "capital": "阿迪斯阿貝巴Addis Ababa",
    "population": "96.6 Million (2013)",
    "faith": [{
        "name": "伊斯蘭教",
        "percentage": 33.9
      }, {
        "name": "衣索比亞正教",
        "percentage": 43.5
      }, {
        "name": "基督新教",
        "percentage": 18.6
      }, {
        "name": "天主教",
        "percentage": 0.7
      }, {
        "name": "原始信仰",
        "percentage": 2.6
      }
    ],
    "economy": [{
        "name": "一級產業-咖啡",
        "percentage": 47
      }, {
        "name": "二級產業-初級加工、紡織",
        "percentage": 10.8
      }, {
        "name": "三級產業",
        "percentage": 42.2
      }
    ]
  },
  {
    "iso": "BFA",
    "country": "布吉納法索 Burkina Faso",
    "introduction": "舊稱上伏塔（法語：Haute Volta），1984年8月改為現國名。布吉納法索為文明古國，建國歷史近千年，可上溯至11世紀之「摩西皇朝」，「布吉納法索」的意思是「君子之國」，因其人民素以老實勤奮著稱。",
    "symbol": "乳油木果、非洲電影節",
    "currency": "西非法郎 (FCFA)",
    "language": "法語",
    "flag": "BurkinaFaso_Flag.png",
    "emblem": "BurkinaFaso_emblem.jpg",
    "headOfState": "總統：Michel Kafando 總理：Yacouba Issac ZIDA",
    "politics": "議會制",
    "atmosphere": "布吉納法索以熱帶草原氣候為主，年降水量介於500～1000毫米，南多北少。",
    "geography": "全境無沙漠，北方緊鄰沙漠邊緣，西部地區土壤多沙，南部為草原，作物及水果多產於中南部。",
    "capital": "瓦加杜古 Ouagadougou (簡稱Ouaga）",
    "population": "15 Million",
    "faith": [{
        "name": "天主/基督新教",
        "percentage": 23.2
      }, {
        "name": "伊斯蘭教",
        "percentage": 60.5
      }, {
        "name": "當地信仰",
        "percentage": 15.3
      }, {
        "name": "無信仰",
        "percentage": 1
      }
    ],
    "economy": [{
        "name": "一級產業-棉花、芝麻、乳油木果、花生、高粱",
        "percentage": 38
      }, {
        "name": "二級產業-棉製品加工、肥皂製作、農產品加工",
        "percentage": 22
      }, {
        "name": "三級產業",
        "percentage": 40
      }
    ]
  },
  {
    "iso": "GHA",
    "country": "迦納 Ghana",
    "introduction": "迦納曾受葡萄牙、荷蘭、英國、丹麥、德國、瑞典等國殖民，1897年全境淪為英國殖民地，稱「黃金海岸」，1957年3月6日宣佈獨立，改名為迦納。",
    "symbol": "可可",
    "currency": "迦納賽地 (GHS)",
    "language": "英語",
    "flag": "Ghana_Flag.png",
    "emblem": "Ghana_emblem_svg.png",
    "headOfState": "總統：John Dramani Mahama 副總統：Kwesi Amissah-Arthur",
    "politics": "單一制、總統制",
    "atmosphere": "氣候乾濕季分明，沿海平原和西南部阿散蒂高原屬熱帶雨林氣候，伏塔河谷和北部高原地區屬熱帶草原氣候，氣溫較高，降雨量由西南往東北遞減。",
    "geography": "迦納近赤道，擁有典型的熱帶氣候，全年氣溫在18℃～40℃之間。北部屬於又熱又乾燥的氣候，盛產西瓜。東南海岸氣候溫暖乾燥，西南則是潮濕炎熱。",
    "capital": "阿克拉 Accra",
    "population": "24 Million",
    "faith": [{
        "name": "天主/基督新教",
        "percentage": 71.2
      }, {
        "name": "伊斯蘭教",
        "percentage": 17.6
      }, {
        "name": "當地信仰",
        "percentage": 5.2
      }, {
        "name": "無信仰",
        "percentage": 5.2
      }
    ],
    "economy": [{
        "name": "一級產業-可可、木薯、乳油木果、米、玉米、花生、木材",
        "percentage": 22
      }, {
        "name": "二級產業-輕工業、小型商業造船、食品加工、石油加工、農產品加工",
        "percentage": 28.4
      }, {
        "name": "三級產業",
        "percentage": 49.6
      }
    ]
  },
  {
    "iso": "STP",
    "country": "聖多美普林西比 São Tomé and Príncipe",
    "introduction": "位於非洲中西部幾內亞灣，由聖多美島、普林西比島和附近一些礁、嶼組成。 十九世紀早期，引進了兩種經濟作物：咖啡與可可，當地肥沃的火山土壤特別適合這些新的經濟作物。到了1908年，聖多美成了世界最大的可可產地，可可到現在還是該國最重要的作物。",
    "symbol": "火山",
    "currency": "多布拉 (STD)",
    "language": "葡萄牙語",
    "flag": "Sao_Tome_and_Principe_Flag_svg.png",
    "emblem": "São_Tomé_&_Príncipe_Emblem.png",
    "headOfState": "總統：Manuel Pinto da Costa 總理：Patrice Trovoada",
    "politics": "共和制",
    "atmosphere": "熱帶雨林氣候，終年高溫多雨。年降水量1000～3000毫米，兩島西南迎風坡達5000毫米。",
    "geography": "聖多美島及普林西比島皆為火山島，島上植被茂盛，擁有許多高山及交錯的河流",
    "capital": "聖多美 Sao tome",
    "population": "194,006",
    "faith": [{
        "name": "天主/基督新教",
        "percentage": 97
      }, {
        "name": "伊斯蘭教",
        "percentage": 2
      }, {
        "name": "當地信仰",
        "percentage": 1
      }
    ],
    "economy": [{
        "name": "一級產業-可可（占出口總值的3/4）、咖啡、椰子、香蕉、木瓜、棕櫚仁、肉桂",
        "percentage": 18.8
      }, {
        "name": "二級產業-輕工業、魚類加工、鋸木廠、肥皂廠",
        "percentage": 16.1
      }, {
        "name": "三級產業",
        "percentage": 65.1
      }
    ]
  },
  {
    "iso": "TGO",
    "country": "多哥 Togo",
    "introduction": "西非國家之一，國名在當地語言是「水邊」的意思。從15世紀起，葡萄牙、英國、法國等殖民者侵入沿岸販賣奴隸，稱為「奴隸海岸」。",
    "symbol": "巫毒的發源地。一片漆黑的夜景",
    "currency": "西非法郎 (FCFA)",
    "language": "法語",
    "flag": "Togo_Flag.png",
    "emblem": "Togo_emblem.jpg",
    "headOfState": "總統：Faure Essozimna Gnassingbé 總理：Komi Sélom Klassou",
    "politics": "共和制",
    "atmosphere": "北部為乾燥少雨的熱帶草原氣候，南部為熱帶雨林氣候",
    "geography": "國土為南北狹長型狀，北部為起伏平緩的熱帶草原，中部多為山地，南部為平原，沿海低地多潟湖與沼澤",
    "capital": "洛美 Lome",
    "population": "7.5 Million",
    "faith": [{
        "name": "天主/基督新教",
        "percentage": 29
      }, {
        "name": "伊斯蘭教",
        "percentage": 20
      }, {
        "name": "當地信仰",
        "percentage": 51
      }
    ],
    "economy": [{
        "name": "一級產業-可可（占出口總值的3/4）、咖啡、椰子、山藥、木薯、豆類",
        "percentage": 27.6
      }, {
        "name": "二級產業-農產加工、礦業、手工雕刻",
        "percentage": 33.9
      }, {
        "name": "三級產業",
        "percentage": 38.5
      }
    ]
  },
  {
    "iso": "BEN",
    "country": "貝寧 Benin",
    "introduction": "貝寧被認定為經濟開發最落後的國家之一，全國以務農為主，因南部的部落王國早期就與歐洲列強有密切往來，農業經濟太早專業化，導致糧食作物無法自給。棉花的種植方式比其他非洲國家細緻，因此質量較好。",
    "symbol": "巫毒為國教",
    "currency": "西非法郎 (FCFA)",
    "language": "法語",
    "flag": "Benin_Flag.png",
    "emblem": "Benin_emblem.png",
    "headOfState": "總統：Yayi Boni",
    "politics": "共和制",
    "atmosphere": "北部為乾燥少雨的熱帶草原氣候，南部為熱帶雨林氣候",
    "geography": "南部海岸屬於沙嘴和潟湖地，多為古河口灣侵蝕和淤積的產物。沿海區以北為土質肥沃的黏土區，西北部有高山，東北部為尼日河平原",
    "capital": "新港 亦可稱波多諾夫 Porto-Novo",
    "population": "10 Million",
    "faith": [{
        "name": "天主/基督新教",
        "percentage": 42.8
      }, {
        "name": "伊斯蘭教",
        "percentage": 24.4
      }, {
        "name": "伏督Vodoo",
        "percentage": 17.3
      }, {
        "name": "當地信仰",
        "percentage": 9.0
      }, {
        "name": "無信仰",
        "percentage": 6.5
      }
    ],
    "economy": [{
        "name": "一級產業-棉花、木薯、棕櫚油、腰果、玉米",
        "percentage": 31.8
      }, {
        "name": "二級產業-紡織、建材製作、水泥製造",
        "percentage": 12.3
      }, {
        "name": "三級產業",
        "percentage": 55.9
      }
    ]
  },
  {
    "iso": "SEN",
    "country": "塞內加爾 Senegal",
    "introduction": "為法國殖民時期的重要據點，故其文化及文學發達。女權意識高，不少中小學皆以對社會有傑出貢獻之女姓文學家、政治家等的名字命名，並在其校內設立該女性之展示館。",
    "symbol": "文學",
    "currency": "西非法郎 (FCFA)",
    "language": "法語",
    "flag": "Senegal_Flag.png",
    "emblem": "Senegal_emblem.png",
    "headOfState": "總統：Macky Sall 總理：Mohammed Dionne",
    "politics": "半總統制",
    "atmosphere": "受信風帶影響，屬夏雨冬乾型的熱帶莽原氣候，中部和東部大部分為半沙漠地帶。年雨量約600公釐，由南向北遞減，雨季為六月至十月。最高月均溫27℃，最低月均溫17℃，愈內陸愈低溫。",
    "geography": "塞內加爾位於非洲大陸的西部， 地形主要為平原，東部和東南部有丘陵高地，沿岸多起伏的沙丘。",
    "capital": "達卡 Dakar",
    "population": "11 Million",
    "faith": [{
        "name": "天主/基督新教",
        "percentage": 4.2
      }, {
        "name": "伊斯蘭教",
        "percentage": 95.4
      }, {
        "name": "當地信仰",
        "percentage": 0.4
      }
    ],
    "economy": [{
        "name": "一級產業-花生、棉花、稻米、漁業、玉米、漁業、畜牧業",
        "percentage": 15.6
      }, {
        "name": "二級產業-農業與漁業加工、礦業、肥料製造、石油煉造、船體製造與修復",
        "percentage": 23.8
      }, {
        "name": "三級產業",
        "percentage": 60.6
      }
    ]
  },
  {
    "iso": "MRT",
    "country": "毛利坦尼亞 Mauritania",
    "introduction": "全名茅利塔尼亞伊斯蘭共和國，是西非阿拉伯國家之一。 茅利塔尼亞少數區域尚有奴隸制存在，民族組成為40%的白摩爾人（為阿拉伯－柏柏爾血統），另外黑摩爾人（阿拉伯文化語言傳統的哈拉廷人）和非洲黑人各佔30%。",
    "symbol": "漁業、摩爾人的婚禮儀式",
    "currency": "烏吉拉 (MRO)",
    "language": "阿拉伯語、法語",
    "flag": "Mauritania_Flag.png",
    "emblem": "Mauritania_emblem.png",
    "headOfState": "總統：Mohamed Ould Abdel Aziz 總理：Moulaye Ould Mohamed Laghdaf",
    "politics": "多黨制",
    "atmosphere": "熱帶沙漠氣候；氣候炎熱乾旱， 最冷月均溫仍達攝氏20度以上，3月到4月間並有沙塵暴",
    "geography": "全境有一半國土屬撒哈拉沙漠，西南部有些許草原地形",
    "capital": "諾克少 Nouakchott",
    "population": "3.6 Million",
    "faith": [{
        "name": "伊斯蘭教",
        "percentage": 99
      }, {
        "name": "當地信仰",
        "percentage": 1
      }
    ],
    "economy": [{
        "name": "一級產業-椰棗、稻米、高粱、玉米、漁業、畜牧業",
        "percentage": 17.1
      }, {
        "name": "二級產業-石油生產、礦業（鐵礦）",
        "percentage": 48.7
      }, {
        "name": "三級產業",
        "percentage": 34.2
      }
    ]
  },
  {
    "iso": "MLI",
    "country": "馬利 Mali",
    "introduction": "西非內陸國家、西非國土面積第二大國，過去被稱為法屬蘇丹，源自馬利帝國。該國中部大城廷巴克圖是古帝國 (迦納、馬利、桑海帝國) 在跨撒哈拉貿易中的一個關鍵城市和學術中心。",
    "symbol": "傑內大教堂 廷巴克圖 Timbuktou",
    "currency": "西非法郎 (FCFA)",
    "language": "法語",
    "flag": "Mali_Flag.png",
    "emblem": "Mali_emblem.png",
    "headOfState": "總統：Ibrahim Boubacar Keïta 總理：Modibo Keita",
    "politics": "議會民主制",
    "atmosphere": "馬利的氣候從熱帶溫暖的氣候一直到撒哈拉沙漠的沙漠氣候。 南部年降雨量可達1000毫米，北部有些地方終年不雨。 南部是潮濕的草原，向北演變成灌木草原、半沙漠和沙漠。",
    "geography": "全境平坦，除西南部之外，多壟罩於撒哈拉沙漠之下，為沙漠平原",
    "capital": "巴馬科 Bamako",
    "population": "14 Million",
    "faith": [{
        "name": "天主/基督新教",
        "percentage": 5.0
      }, {
        "name": "伊斯蘭教",
        "percentage": 90.0
      }, {
        "name": "當地信仰",
        "percentage": 5.0
      }
    ],
    "economy": [{
        "name": "一級產業-棉花、米、玉米、花生、高粱，北方則有小麥；芒果、洛神花和薑出口至西歐",
        "percentage": 38
      }, {
        "name": "二級產業-礦業、建築、食品加工",
        "percentage": 23.3
      }, {
        "name": "三級產業",
        "percentage": 38.7
      }
    ]
  },
  {
    "iso": "GMB",
    "country": "甘比亞 Republic of the Gambia",
    "introduction": "全名為甘比亞共和國，西非國家之一 ，陸上被塞內加爾環繞，是非洲大陸最小的國家。1965年甘比亞脫離英國獨立，是世界上最低度開發國家之一。",
    "symbol": "孕育歐洲列強奴隸貿易的甘比亞河",
    "currency": "達拉西 (GMD)",
    "language": "英語",
    "flag": "Gambia_flag.png",
    "emblem": "Gambia_Emblem.png",
    "headOfState": "總統：Yahya Jammeh",
    "politics": "總統制",
    "atmosphere": "全境屬熱帶氣候，乾濕季分明",
    "geography": "國土沿著甘比亞河為河谷狹長平原，水網密布，多季節性氾濫成沼澤。",
    "capital": "班竹 Banjul (舊稱巴瑟斯特)",
    "population": "1.7 Million",
    "faith": [{
        "name": "天主/基督新教",
        "percentage": 4.1
      }, {
        "name": "伊斯蘭教",
        "percentage": 95.3
      }, {
        "name": "當地信仰",
        "percentage": 0.6
      }
    ],
    "economy": [{
        "name": "一級產業-米、玉米、花生、高粱、漁業",
        "percentage": 22.8
      }, {
        "name": "二級產業-農業機械組裝、服務紡織、榨油、花生加工、魚類加工、木雕首飾製作",
        "percentage": 11.8
      }, {
        "name": "三級產業-旅遊業盛行",
        "percentage": 65.5
      }
    ]
  },
  {
    "iso": "TCD",
    "country": "查德Chad",
    "introduction": "查德地處非洲中心，遠離海洋，全年高溫炎熱，且國土大部份為沙漠地區，所以又被稱為「非洲死亡之心」。",
    "symbol": "查德湖",
    "currency": "中非法郎 Central African CFA franc",
    "language": "法語、阿拉伯語",
    "flag": "Chad_flag.png",
    "emblem": "Chad_coat.png",
    "headOfState": "總統：Idriss Déby Itno 總理：Djimrangar Dadnadji",
    "politics": "半總統制、共和制",
    "atmosphere": "北部的沙漠地區，屬熱帶沙漠氣候；中部乾旱的薩赫勒地區，屬熱帶草原氣候；和南部較肥沃的蘇丹草原地區，屬熱帶雨林氣候",
    "geography": "該國最明顯的地理特徵：一片被北部、東部和南部的山脈包圍的盆地。查德的國名源於查德湖，查德湖現在是非洲的第二大濕地。位於提貝斯提高原的火山庫西山高3,414米，是查德以至撒哈拉地區的最高山峰",
    "capital": "恩將納N'Djamena",
    "population": "13.2 Million(2014)",
    "faith": [{
        "name": "穆斯林",
        "percentage": 54
      }, {
        "name": "羅馬天主教徒",
        "percentage": 20
      }, {
        "name": "新教徒",
        "percentage": 14
      }, {
        "name": "泛靈論者",
        "percentage": 10
      }, {
        "name": "無神論者",
        "percentage": 3
      }
    ],
    "economy": [{
        "name": "一級產業-米、蜀黍、花生、馬鈴薯",
        "percentage": 46.3
      }, {
        "name": "二級產業-棉織布、石油、肥皂、菸草",
        "percentage": 9.9
      }, {
        "name": "三級產業",
        "percentage": 43.8
      }
    ]
  },
  {
    "iso": "SLE",
    "country": "獅子山共和國Republic of Sierra Leone",
    "introduction": "由於礦產豐富，獅子山的經濟主要依賴礦業，其中最為世人所知的是從獅子山開採的血鑽石。之後由於礦業沒落、內戰，導致經濟衰退，2001年戰爭結束後外國援助湧入幫助獅子山重建。",
    "symbol": "礦業（血鑽石）",
    "currency": "里昂Leone",
    "language": "英語",
    "flag": "Sierra_Leone_flag.png",
    "emblem": "Sierra_Leone_coat.png",
    "headOfState": "總統：Ernest Bai Koroma",
    "politics": "共和國",
    "atmosphere": "熱帶雨林氣候，7、8月降水最多，多雷暴雨；年降水量內陸在1000毫米以上，沿海達3000-4000毫米。",
    "geography": "獅子山境內大部是丘陵、高原，地勢東高西低，一般海拔300-600米，最高峰為洛馬山脈（Loma Mt.）海拔1947米；沿岸多低地、沙洲和澙湖",
    "capital": "自由城 Freetown",
    "population": "6.1 Million(2013)",
    "faith": [{
        "name": "伊斯蘭教",
        "percentage": 60
      }, {
        "name": "基督教",
        "percentage": 30
      }, {
        "name": "傳統宗教或其他宗教",
        "percentage": 10
      }
    ],
    "economy": [{
        "name": "一級產業-可可、米、咖啡、 家禽、棕櫚油",
        "percentage": 42.5
      }, {
        "name": "二級產業-鑽石礦產、織布、菸草",
        "percentage": 26.8
      }, {
        "name": "三級產業",
        "percentage": 30.7
      }
    ]
  },
  {
    "iso": "CIV",
    "country": "象牙海岸共和國 République de Côte d'Ivoire（Ivory Coast）",
    "introduction": "象牙海岸在冷戰時期曾是最繁盛的西非熱帶國家之一，但1985年後，由於政治腐敗，加上缺乏改革，國內的騷動、2002-2011年間的內戰，致使經濟一蹶不振。",
    "symbol": "咖啡、可可",
    "currency": "西非法郎Western African CFA franc",
    "language": "法語",
    "flag": "Côte_d'Ivoire_flag.png",
    "emblem": "Ivory_Coast_coat.png",
    "headOfState": "總統：Alassane Dramane Ouattara 總理：Guillaume Soro",
    "politics": "總統制，但在總統之下另設總理領導內閣，其政體實質為由一黨專政和軍人統治逐漸建立民主的過渡型政體。地方行政方面實行單一制。",
    "atmosphere": "全境屬熱帶海洋氣候，全年分雨季與乾季，5至7月為大雨季，8至11月為小雨季，其餘月份為乾季，年平均溫度為攝氏27度，南部雨量較北部多，年平均降雨量1,400公釐。",
    "geography": "全國地勢由南向北逐漸加高，中部有少數海拔914到1524公尺的山峰，高原表面由砂礫所構成。自南部海岸穿越全國直到北方邊境，可以明顯地區分為鹹水湖、森林和草原等三個地區[",
    "capital": "雅穆索戈Yamoussoukro",
    "population": " 22.7 Million(2014)",
    "faith": [{
        "name": "象國回教徒（主要係西非移民）",
        "percentage": 38.6
      }, {
        "name": "基督教",
        "percentage": 32.8
      }, {
        "name": "傳統宗教或其他宗教",
        "percentage": 28.6
      }
    ],
    "economy": [{
        "name": "一級產業-咖啡、可可豆、玉米、米、番薯、木材",
        "percentage": 26.3
      }, {
        "name": "二級產業-棕櫚油、鑽石、橡膠製業",
        "percentage": 21.3
      }, {
        "name": "三級產業",
        "percentage": 52.4
      }
    ]
  },
  {
    "iso": "LBR",
    "country": "賴比瑞亞（ the Republic of Liberia ）",
    "introduction": "賴比瑞亞，為19世紀初，一些美國黑奴解放後所建立、移居的國家。所以國名在英文有「自由」（liberty）和「解放」（liberated）的意思。",
    "symbol": "國旗",
    "currency": "賴比瑞亞元（LRD）",
    "language": "英語",
    "flag": "Liberia_flag.png",
    "emblem": "Liberia_coat.png",
    "headOfState": "總統：Ellen Johnson Sirleaf ",
    "politics": "總統制",
    "atmosphere": "賴比瑞亞地近赤道；雖然也屬熱帶氣候，但郤沒有熱帶通常有的炎熱和瘴濕及不適於健康的氣候。最熱的月份是二月和三月，氣溫可達32.2度(華氏90度）。最冷的月份是八月和九月，白天的氣溫可降到18.3度（華氏65度）。",
    "geography": "賴比瑞亞海岸線長537公里。屬熱帶季風氣候，年平均氣溫約25℃。",
    "capital": "蒙羅維亞Monrovia",
    "population": "4 Million(2015)",
    "faith": [{
        "name": "基督教",
        "percentage": 40
      }, {
        "name": "傳統信仰",
        "percentage": 40
      }, {
        "name": "伊斯蘭教",
        "percentage": 15
      }, {
        "name": "其他",
        "percentage": 5
      }
    ],
    "economy": [{
        "name": "一級產業-橡膠、咖啡、可可、米、棕櫚油、蔗糖、香蕉",
        "percentage": 76.9
      }, {
        "name": "二級產業-棕櫚油、鑽石、橡膠製業",
        "percentage": 5.4
      }, {
        "name": "三級產業",
        "percentage": 17.7
      }
    ]
  },
  {
    "iso": "AGO",
    "country": "安哥拉Angola",
    "introduction": "安哥拉地大物博，未開發的資源十分豐富，且為葡萄牙屬地，因而有「非洲的巴西」之稱，因石油生產而經濟快速成長。",
    "symbol": "礦產（鑽石、黃金）",
    "currency": "安哥拉匡撒（AOA）",
    "language": "葡萄牙語",
    "flag": "Angola_flag.png",
    "emblem": "Angola_coat.png",
    "headOfState": "總統：José Eduardo dos Santos",
    "politics": "總統制",
    "atmosphere": "安哥拉大部分地區屬熱帶草原氣候，每年有溼季（10月~3月）及旱季（4月~9月），位在高原上的夫安波一帶，海拔有1500公尺，氣候溫和，年平均降雨量1450公釐，日平均氣溫為攝氏24至29度。濱海地區的氣溫和雨量均很低。羅安達以南屬半乾燥氣候，羅安達則是典型的草原氣候",
    "geography": "安哥拉西部有濱大西洋的狹窄平原，北部鄰近剛果三角洲一帶地形開闊。內陸為比耶高原，為各大水系的分水嶺，有「安哥拉屋脊」之稱，平均海拔1200公尺，最高點莫寇峰（2619公尺）。境內多河流，但大多不通航運。",
    "capital": "羅安達Luanda",
    "population": "19 Million(2010)            ",
    "faith": [{
        "name": "天主教",
        "percentage": 70
      }, {
        "name": "土著信仰",
        "percentage": 10
      }, {
        "name": "新教",
        "percentage": 20
      }
    ],
    "economy": [{
        "name": "一級產業-香蕉、蔗糖、咖啡、玉米、菸草、漁業",
        "percentage": 10.2
      }, {
        "name": "二級產業-鑽石、鈾、黃金、長石、礬土",
        "percentage": 61.4
      }, {
        "name": "三級產業",
        "percentage": 28.4
      }
    ]
  },
  {
    "iso": "GIN",
    "country": "幾內亞Guinea(République de Guinée)",
    "introduction": "幾內亞本來是指非洲撒哈拉沙漠以南，幾內亞灣以北的整個地區，它來源於柏柏爾語，意思大約是「黑人的國家」。",
    "symbol": "",
    "currency": "幾內亞法郎（GNF）",
    "language": "法語",
    "flag": "Guinea_flag.png",
    "emblem": "Guinea_coat.png",
    "headOfState": "總統：Alpha Condé 總理：Ahmed Tidiane Souaré",
    "politics": "共和制",
    "atmosphere": "幾內亞沿海地區為熱帶季風氣候，內地為熱帶草原氣候。年降水量內陸為1000～1500毫米，沿海達4000毫米。",
    "geography": "",
    "capital": "柯那克里Conakry",
    "population": "12 Million",
    "faith": [{
        "name": "遜尼派伊斯蘭教",
        "percentage": 87
      }, {
        "name": "天主教",
        "percentage": 5
      }, {
        "name": "拜物教",
        "percentage": 8
      }
    ],
    "economy": [{
        "name": "一級產業-香咖啡、鳳梨、香蕉、馬鈴薯",
        "percentage": 22.9
      }, {
        "name": "二級產業-鑽石、黃金、鐵、輕工業",
        "percentage": 46.5
      }, {
        "name": "三級產業",
        "percentage": 30.6
      }
    ]
  },
  {
    "iso": "NGA",
    "country": "奈及利亞Federal Republic of Nigeria",
    "introduction": "奈及利亞是全非洲人口最多的國家，它被列為是未來11國中的一員，而且還是大英國協成員。",
    "symbol": "石油、奈萊塢",
    "currency": "奈拉（NGN）",
    "language": "英語",
    "flag": "Nigeria_flag.png",
    "emblem": "Nigeria_coat.png",
    "headOfState": "總統：Muhammadu Buhari",
    "politics": "聯邦制、總統制",
    "atmosphere": "奈及利亞位於熱帶地區，氣候潮濕。主要是熱帶草原氣候。西南部拉哥斯受幾內亞暖流影響，自北向南年降水量200-3000毫米。",
    "geography": "奈及利亞北部有阿達馬瓦高原、曼比拉高原、喬斯高原和奧布杜高原等,南部主要是尼日河下游沖積平原，東南邊境多山，沿海多沙洲、沼澤和潟湖。",
    "capital": "阿布加Abuja",
    "population": "174 Million (2013)",
    "faith": [{
        "name": "基督教",
        "percentage": 44.2
      }, {
        "name": "伊斯蘭教",
        "percentage": 52.6
      }, {
        "name": "傳統宗教",
        "percentage": 3.2
      }
    ],
    "economy": [{
        "name": "一級產業-可可豆、棉、棕梠樹",
        "percentage": 20.6
      }, {
        "name": "二級產業-石油、煤礦、橡膠製品",
        "percentage": 25.6
      }, {
        "name": "三級產業-工業、化學製品",
        "percentage": 53.8
      }
    ]
  },
  {
    "iso": "SDN",
    "country": "蘇丹（北蘇丹）Republic of the Sudan",
    "introduction": "曾被失敗國家指數列表評為「世界上最不安定的國家」，歸咎於軍政府在達佛戰亂問題上的專制統治。同時，南蘇丹於2011年1月9日舉行公民投票，98.83％的投票支持獨立。2011年7月9日，南蘇丹正式宣布獨立。",
    "symbol": "紋面",
    "currency": "蘇丹鎊（SDG）",
    "language": "阿拉伯語、英語",
    "flag": "Sudan_flag.png",
    "emblem": "Sudan_Emblem.png",
    "headOfState": "عمر حسن احمد البشير：總統",
    "politics": "國家結構形式：聯邦制 國家政權：共和國 政治體制：總統制",
    "atmosphere": "蘇丹終年炎熱，主要屬熱帶莽原和沙漠氣候，年降水量自北向南由20多毫米遞增至1000毫米以上，北半部多沙漠，南半部多草原、森林和沼澤",
    "geography": "中部是蘇丹盆地，尼羅河河谷貫穿，青尼羅河、白尼羅河匯合處一帶土質最為肥沃，西部和東部是高原。",
    "capital": "喀土木Khartoum",
    "population": "40 Million",
    "faith": [{
        "name": "遜尼派伊斯蘭教",
        "percentage": 40
      }, {
        "name": "基督教",
        "percentage": 5
      }, {
        "name": "傳統宗教",
        "percentage": 55
      }
    ],
    "economy": [{
        "name": "一級產業-棉花、花生、稷、甘蔗",
        "percentage": 26.8
      }, {
        "name": "二級產業-織布、石油、水泥、糖",
        "percentage": 35.6
      }, {
        "name": "三級產業-工業、化學製品",
        "percentage": 37.6
      }
    ]
  },
  {
    "iso": "SSD",
    "country": "南蘇丹（Republic of South Sudan）",
    "introduction": "南蘇丹原是英埃共管蘇丹的一部分，1956年蘇丹共和國獨立後成為其一部分，被劃分為南部10省。之後爆發了兩次蘇丹內戰，第二次內戰於1983年爆發，至2005年才簽署《全面和平條約》，成立蘇丹南方自治政府。2011年，南蘇丹獨立公投通過，遂於2011年7月9日宣告獨立。",
    "symbol": "世界上最年輕的國家",
    "currency": "南蘇丹鎊（SSP）",
    "language": "英語",
    "flag": "South_Sudan_flag.png",
    "emblem": "South_Sudan_coat.png",
    "headOfState": "總統：Salva Kiir Mayardit",
    "politics": "國家結構形式：聯邦制 政治體制：總統制、共和制、民主制",
    "atmosphere": "氣候以熱帶乾濕季氣候為主，全年四季變化不明顯。每年5月至10月為雨季，11月至翌年4月為旱季。",
    "geography": "",
    "capital": "朱巴Juba",
    "population": "11 Million",
    "faith": "南蘇丹共和國以黑人為主，以信仰泛靈論佔多數，少數信仰基督新教、天主教、科普特教派和伊斯蘭教等宗教，不同於主要信奉伊斯蘭教、以阿拉伯人為主並占多數的蘇丹共和國。",
    "economy": [{
        "name": "一級產業-米、小麥、甘蔗、椰子、番薯、太陽花種子、豆子、芝麻種子、花生",
        "percentage": 85
      }, {
        "name": "其他",
        "percentage": 15
      }
    ]
  },
  {
    "iso": "COG",
    "country": "剛果共和國 Republic of Congo",
    "introduction": "二戰期間，這裡是「自由法國」象徵性之地。現在利用自身地理位置的優勢，由政府主導致力發展為全非洲的陸海空三方物流中心。",
    "symbol": "漠南非洲的民選制度楷模 (1990年，剛果執政黨提議廢除一黨獨大制，隔年，第一次民選總統出任，次年由民選制度所建立的政府成立。此舉無疑是替漠南非洲率先做出了民主選舉與多黨共和的楷模。 資料來源：http://goo.gl/cjgYPQ)",
    "currency": "剛果法郎 (CDF)",
    "language": "法語",
    "flag": "Republic_of_Congo_flag.png",
    "emblem": "the_Republic_of_Congo_emblem.gif",
    "headOfState": "總統：Denis Sassou-Nguesso    總理：Isidore Mvouba",
    "politics": "共和制",
    "atmosphere": "北、中部：熱帶雨林氣候。年均溫高、濕度大。 南部：為熱帶草原氣候、終年高溫、明顯乾濕季。",
    "geography": "剛果處於非洲中西部，地跨赤道 。 北部屬剛果盆地，多沼澤；南部是高原，沿海有狹窄低地。",
    "capital": "Brazzaville  布拉薩市",
    "population": "43 Million",
    "faith": [{
        "name": "天主教",
        "percentage": 45
      }, {
        "name": "新教",
        "percentage": 24
      }, {
        "name": "原始宗教",
        "percentage": 30
      }, {
        "name": "其他",
        "percentage": 1
      }
    ],
    "economy": [{
        "name": "一級產業-樹薯、熱帶栽培業作物",
        "percentage": 3.3
      }, {
        "name": "二級產業-石油、林業、棕梠油、香菸",
        "percentage": 74
      }, {
        "name": "三級產業-轉口貿易、服務業",
        "percentage": 22
      }
    ]
  },
  {
    "iso": "COD",
    "country": "剛果民主共和國 the demoncratic republic of Congo",
    "introduction": "曾為比利時殖民地，1960年獨立，非洲國土第二大國家，非洲國家人口第四大國。 境內礦產資源豐沛，有「原料倉庫」之稱。另外，首都金夏沙是中部非洲最重要的文化及知識中心，許多藝術家社群於此駐點。",
    "symbol": "1. 熱帶雨林 (僅次於亞馬遜雨林，世界第二大) 2.Rumble in the Jungle (剛果舉辦過世界上規模最大的拳擊賽，其中最著名的參賽者是Muhamed Ali(拳王阿里) 和George Forman。 3.Kinshasa Fashion Week, KFW (以推廣剛果時尚為主，作為非洲籍服裝設計師與非洲服飾品牌的伸展台，標榜布料生產與服裝設計皆為Made in Congo。)",
    "currency": "剛果法郎 (CDF)",
    "language": "法語 ",
    "flag": "the_Democratic_Republic_of_the_Congo_flag.png",
    "emblem": "the_Democratic_Republic_of_the_Congo_emblem.png",
    "headOfState": "總統：Joseph Kabila Kabange 總理：Augustin Matata Ponyo Mapon",
    "politics": "半總統制 共和制",
    "atmosphere": "熱帶氣候區，濕熱多雨。 【全境】 乾濕兩季，6月到10月是乾季，11月到隔年5月是雨季。 【區域差異】 北部：日夜溫差大，最高可差攝氏20度 南部、東部：位處高原，涼爽乾燥",
    "geography": "橫跨赤道的國家，國境佔剛果盆地的絕大部份，並且被支流密布的剛果河所灌溉；除中下游有較大的平原外，其餘東、北、南三面都被高原和山地所環繞，西南部剛果河下游一隅瀕大西洋，海岸線只有37公里長。",
    "capital": "Kinshasa 金夏沙",
    "population": "77 Million",
    "faith": [{
        "name": "天主教",
        "percentage": 45
      }, {
        "name": "新教",
        "percentage": 24
      }, {
        "name": "原始宗教",
        "percentage": 17.5
      }, {
        "name": "金邦古教",
        "percentage": 13.5
      }
    ],
    "economy": [{
        "name": "一級產業-礦業、熱帶農作物棕梠和咖啡、農業、漁業、林業",
        "percentage": 44
      }, {
        "name": "二級產業-礦業加工、民生用品製造、食品加工、水泥",
        "percentage": 21
      }, {
        "name": "三級產業-物流服務",
        "percentage": 35
      }
    ]
  },
  {
    "iso": "DJI",
    "country": "吉布地 Djibouti",
    "introduction": "位處非洲、中東、歐洲三地交界之處，戰略位置重要。吉布地港具有東非少數大型的現代化國際港口設施，轉口貿易是該國重要的收入來源，但國內缺乏自然資源，工農業基礎薄弱，政局不穩。 ",
    "symbol": "1.吉布地港 (非洲之角國家中最安全、發展最穩定的港口，同時為內陸國衣索比亞唯一合作對外港口) 2.大馬阿里火山 Dama Ali 與阿貝湖 Lake Abbe (阿貝湖是座船舶可航行的湖，周圍都是小型活火山，其中規模與阿貝湖一樣大的火山叫Dama Ali。 資訊連結：http://goo.gl/MNLiF6)  ",
    "currency": "吉布地法郎 (DJF)",
    "language": "法語 阿拉伯語 ",
    "flag": "Djibouti_flag.png",
    "emblem": "Djibouti_emblem.png",
    "headOfState": "總統：Ismaaciil Cumar Geelle  總理：Dileita Mohamed Dileita",
    "politics": "半總統制 共和制",
    "atmosphere": "【全境】全年分涼、熱季，4月至10月為酷熱，最高溫可達攝氏45度以上； 11月至次年三月，為涼季。 【區域】 沿海地帶為熱帶沙漠氣候，終年高溫少雨。 內陸以高原及山地為主，氣候較涼爽。 ",
    "geography": "吉布地地處亞丁灣西岸，沿海部分是平原和高原，間有低洼平原和湖泊；西部與南部則是寬廣的高原和山地，海拔500-800米。  除了濱海地帶外，境內大部份土地都是沙漠和草原，無固定河流，只有季節性的小溪流， ",
    "capital": "Djibouti (city) 吉布地市",
    "population": "81萬",
    "faith": [{
        "name": "遜尼派伊斯蘭教",
        "percentage": 94
      }, {
        "name": "基督教",
        "percentage": 6
      }
    ],
    "economy": [{
        "name": "一級產業-畜牧業與漁業",
        "percentage": 3
      }, {
        "name": "二級產業-鹽業、營建業",
        "percentage": 17
      }, {
        "name": "三級產業-轉口貿易",
        "percentage": 80
      }
    ]
  },
  {
    "iso": "GAB",
    "country": "加彭 Gabon",
    "introduction": "擁有豐富的民間傳說與神話故事，並藉由口傳的方式來保存傳統文化；另外，加彭還因各特殊面具在國際上聞名。海上石油生產收入佔全國GDP一半，經濟繁榮。",
    "symbol": "民族面具 民族歌手",
    "currency": "中非法郎 (XAF)",
    "language": "法語 ",
    "flag": "Gabon_flag.png",
    "emblem": "Gabon_emblem.png",
    "headOfState": "總統：Ali Bongo Ondimba 總理：Jean Eyeghe Ndong",
    "politics": "共和制",
    "atmosphere": "南部屬於熱帶草原氣候，北部屬於熱帶雨林氣候， 年降水量內陸為1500毫米以上， 北部沿岸超過2500毫米。",
    "geography": "加彭位於赤道附近中部非洲的大西洋海岸， 為赤道多雨氣候， 國土面積的85%為熱帶雨林所覆蓋。",
    "capital": "Libreville 利柏維爾 (亦可稱自由市)",
    "population": "1 Million",
    "faith": [{
        "name": "基督教",
        "percentage": 55
      }, {
        "name": "其他",
        "percentage": 45
      }
    ],
    "economy": [{
        "name": "一級產業-畜農業",
        "percentage": 3
      }, {
        "name": "二級產業-石油加工處理、礦產加工、林木業與水泥、食品加工",
        "percentage": 63
      }, {
        "name": "三級產業-旅遊",
        "percentage": 34
      }
    ]
  },
  {
    "iso": "ERI",
    "country": "厄立垂亞 Eritrea",
    "introduction": "厄利垂亞曾為義大利殖民區，影響其建築風格，後來成為衣索比亞的屯墾區，1993年舉行了公民投票、獨立。現在，當權政府掌控了所有媒體，所有報導內容都須經過官方審查，當地言論自由受限。",
    "symbol": "Quhaito (位於厄利垂亞南方的Debub地區，古代城市的石柱遺跡)",
    "currency": "奈克法 (ERN)",
    "language": "",
    "flag": "Eritrea_Flag.png",
    "emblem": "Eritre_emblem.png",
    "headOfState": "總統：Isayas Afewerki",
    "politics": "總統制 一黨專政",
    "atmosphere": "【全境】 高原地區氣候宜人，年平均氣溫為17℃。4月～8月為雨季，其餘為旱季。 【區域】 東部和西部低地氣候炎熱乾燥。 紅海沿岸為沙漠區，3月～10月間白天氣溫可達40℃以上。",
    "geography": "位於東非及非洲之角最北部。 西部低地丘陵，東部沿海平原。 境內最高峰為中部高原的安姆巴-索依拉峰（Amba Soira），海拔3013米，最低點為東部平原的科巴爾低地（Kobar），低於海平面75米。",
    "capital": "Asmara 阿斯馬拉",
    "population": "62 萬",
    "faith": "伊斯蘭教、羅馬天主教、新教徒、基督教。",
    "economy": [{
        "name": "一級產業-礦業開採、農業、畜牧業",
        "percentage": 11
      }, {
        "name": "二級產業-農畜產加工、紡織業、塑料加工",
        "percentage": 26
      }, {
        "name": "三級產業-港口轉運貿易",
        "percentage": 63
      }
    ]
  },
  {
    "iso": "BWA",
    "country": "波札那 Botswana",
    "introduction": "1966年9月30日脫離英國宣告獨立，改名為波札那共和國，實施民主化政治， 積極的社會政策與豐富的礦藏，尤其是鑽石礦，佔該國輸出利潤的八成。 讓波札那擁有非洲大部分地區難得一見的開發水準。",
    "symbol": "1. 鑽石、全非洲最不腐敗的國家 2. 奧卡萬戈沼澤 Okavango Delta  (全球最大內陸三角洲、觀光賣點之一)",
    "currency": "普拉 (BWP)",
    "language": "英語 次瓦納語",
    "flag": "Botswana_flag.png",
    "emblem": "Botswana_emblem.jpg",
    "headOfState": "總統：Ian Khama",
    "politics": "總統制",
    "atmosphere": "全境熱帶乾旱草原氣候，除了西部為沙漠、半沙漠氣候",
    "geography": "北方：多草原和鹽沼，馬卡迪卡迪鹽沼（Makgadikgadi Pan）面積廣大。 中部和西南部：屬卡拉哈里沙漠，覆蓋了波札那接近七成土地。 西北方：奧卡萬戈沼澤 (Okavango Delta) 是世上最大的內陸三角洲 東南部：丘陵",
    "capital": "Gaborone 嘉柏隆里",
    "population": "2 Million",
    "faith": [{
        "name": "基督新教",
        "percentage": 71
      }, {
        "name": "傳統宗教",
        "percentage": 6
      }, {
        "name": "其他",
        "percentage": 23
      }
    ],
    "economy": [{
        "name": "一級產業-家畜眷養及農業",
        "percentage": 2
      }, {
        "name": "二級產業-礦產加工、紡織品",
        "percentage": 35
      }, {
        "name": "三級產業-觀光與金融",
        "percentage": 63
      }
    ]
  },
  {
    "iso": "NAM",
    "country": "納米比亞 Namibia",
    "introduction": "經濟以出口礦產為主，非洲第四大非燃料礦物出口國、世界第五大鈾生產國。經濟命脈與鄰國南非緊緊繫絆著，依靠著自然資源讓國家收入豐沛，在加上政局穩定，但因為財富分配不均，導致半數國民仍生活在貧窮線下。",
    "symbol": "納米比亞沙漠 卡拉庫爾羔羊",
    "currency": "奈米比亞元 (NAD)",
    "language": "英文 ",
    "flag": "Namibia_flag.png",
    "emblem": "Namibia_Emblem.png",
    "headOfState": "總統：Hage Gottfried GEINGOB  總理：Nahas Gideon Angula",
    "politics": "半總統制",
    "atmosphere": "全境屬亞熱帶、半沙漠性氣候，乾旱少雨。 ",
    "geography": "納米比亞沿岸有狹窄平原，內陸主要由中央高地組成。 南部多沙漠，北部多草原； 常年有水的河流極少，該國盛產稀有寶石礦物硼鋁石。",
    "capital": "Windhoek 溫荷克",
    "population": "2.1 Million",
    "faith": [{
        "name": "基督教",
        "percentage": 85
      }, {
        "name": "傳統宗教",
        "percentage": 15
      }
    ],
    "economy": [{
        "name": "一級產業-農業、漁業",
        "percentage": 7
      }, {
        "name": "二級產業-類及漁業加工、乳品",
        "percentage": 29
      }, {
        "name": "三級產業-觀光",
        "percentage": 64
      }
    ]
  },
  {
    "iso": "LSO",
    "country": "賴索托 Lesotho",
    "introduction": "位處非洲南部，全世界最大的國中之國，全境完全被南非共和國包圍。因地處高原，賴索托也被稱為「天空王國」。國內就業市場小，人口外移，國家收入主要為移工與僑民的匯入之金流及國際金援。",
    "symbol": "1.巴索托帽 Basotho Hat (當地Basotho族擅長編織，其中以奇特帽子最為出名。賴索托國旗中間的黑色標誌，即是巴索托帽，特色是圓錐狀，帽頂有五個圓環)",
    "currency": "賴索托洛蒂 (LSL)",
    "language": "英語 賽索托語",
    "flag": "Lesotho_flag.gif",
    "emblem": "Lesotho_emblem.jpg",
    "headOfState": "國王：Letsie III 首相：Thomas Motsoahae \"Tom\" Thabane",
    "politics": "君主立憲制 議會民主制",
    "atmosphere": "全境為熱帶季風型濕潤氣候",
    "geography": "賴索托地勢崎嶇，東高西低，地形以山地為主， 其次為平原、丘陵、河谷地帶。 ",
    "capital": "Maseru / Masero 馬賽魯",
    "population": "1 Million",
    "faith":"基督教 80%以上 伊斯蘭教 傳統信仰",
    "economy": [{
        "name": "一級產業",
        "percentage": 7
      }, {
        "name": "二級產業-食品加工業、手工藝品",
        "percentage": 34
      }, {
        "name": "三級產業-旅遊業",
        "percentage": 59
      }
    ]
  },
  {
    "iso": "MUS",
    "country": "模里西斯 Mauritius",
    "introduction": "人口組成多樣，其中超過一半的人口為印度裔民，為非洲國家中唯一信仰印度教超過六成的國家。因為擁有印度洋區域內最大的貨櫃轉運設備，而且對外實施貿易優惠關稅，所以主要經濟來源為國際貨運。",
    "symbol": "【人文藝術：賽卡 Sega】 模里西斯一種本土獨有民間音樂和舞蹈的統稱。塞卡音樂來自非洲，起源自法國殖民統治期間。 亦因此傳統塞卡音樂的歌詞內容通常描述當年黑奴在島上的艱苦生活；到了現代是代表基本人權的尊重。",
    "currency": "模里西斯盧比 (MUR)",
    "language": "英語",
    "flag": "Mauritius_flag.png",
    "emblem": "Mauritius_coat.png",
    "headOfState": "總統：Anerood Jugnauth 總理：Navinchandra Ramgoolam",
    "politics": "議會共和制",
    "atmosphere": "每年5月至10月為冬季，和暖乾燥；11月至4月為夏季，炎熱潮濕。 模里西斯全境屬熱帶氣候，惟受東南信風影響。",
    "geography": "模里西斯是沉浸在海洋中的火山島嶼，山勢從南部陡升到中部往北緩降，除南部一小段海岸線外，整島幾乎均為珊瑚礁包圍。",
    "capital": "Port Louis 路易港",
    "population": "1.2 Million",
    "faith": [{
        "name": "印度教",
        "percentage": 52
      }, {
        "name": "羅馬天主教",
        "percentage": 31
      }, {
        "name": "伊斯蘭教",
        "percentage": 16
      }, {
        "name": "佛教",
        "percentage": 1
      }
    ],
    "economy": [{
        "name": "一級產業-製糖",
        "percentage": 4
      }, {
        "name": "二級產業-紡織業",
        "percentage": 22
      }, {
        "name": "三級產業-海運、旅遊業、金融業",
        "percentage": 74
      }
    ]
  },
  {
    "iso": "SYC",
    "country": "賽席爾",
    "introduction": "是位於非洲大陸東南方，印度洋中西部一個群島國家`,大英國協成員國之一。 推行醫療、教育免費等高福利政策，保持了政局的長期穩定。",
    "symbol": "海耶子、鳥類保育聖地",
    "currency": "塞席爾盧比(SCR)",
    "language": "英語 法語 塞席爾克里奧爾語",
    "flag": "Seychelles_flag.png",
    "emblem": "Seychelles_emblem.png",
    "headOfState": "總統：詹姆斯·米歇爾(James Alix Michel)",
    "politics": "總統制 三權分立",
    "atmosphere": "塞席爾全年高溫，各月之間溫​​差不大，降雨較多，氣候炎熱潮濕，屬熱帶雨林氣候。 ",
    "geography": "塞席爾位處東經55°-56°、南緯4°-5°之間，全國總面積共約455平方公里，塞席爾由40個花崗岩島和45個珊瑚島組成。",
    "capital": "Victoria 維多利亞港",
    "population": "0.9 Million",
    "faith": [{
        "name": "天主教",
        "percentage": 99
      }, {
        "name": "其他",
        "percentage": 1
      }
    ],
    "economy": "農業、漁業、觀光"
  },
  {
    "iso": "ZAF",
    "country": "南非",
    "introduction": "有「彩虹之國」之譽。南非是世界上獨一無二的擁有三個首都的國家。 南非屬於中等收入的發展中國家，也是非洲經濟最發達的國家，資源豐富，財經、法律、通訊、能源、交通業發達，完備的硬體建設和股票交易市場居全球前二十名。",
    "symbol": "黃金 國寶茶",
    "currency": "蘭特（ZAR）",
    "language": "英語",
    "flag": "Republiek_van_Suid_Afrika_FLAG.png",
    "emblem": "Republiek_van_Suid_Afrika_EMBLEM.png",
    "headOfState": "總統：雅各布·祖瑪 (Jacob Gedleyihlekisa Zuma)",
    "politics": "議會制 總統擁有行政實權並對議會負責的議會制",
    "atmosphere": "。西部沿海乾燥無雨。東部屬副熱帶濕潤氣候，西南部屬地中海型氣候，更北部的沙漠地區年降雨量則不足30毫米。",
    "geography": "南非地處非洲高原的最南端，南、東、西三面之邊緣地區為沿海低地，北面則有重山環抱。",
    "capital": "行政首都：普勒托利亞Pretoria 司法首都：布隆泉Bloemfontein 立法首都：開普敦Cape Town",
    "population": "53 Million",
    "faith": "基督教 80% 印度教 伊斯蘭教 傳統信仰",
    "economy": "農業、礦業、鋼鐵業"
  },
  {
    "iso": "GNQ",
    "country": "赤道幾內亞",
    "introduction": "赤道幾內亞大陸部分的原始居民為俾格米人，他們的領地後來被班圖人占有。 葡萄牙航海家斐南·德·波（Fernão do Pó）在尋找通往印度的航路過程中發現了斐南多波島，將其命名為「福爾摩薩」（Formosa）。安諾本島是在新年發現的，並由此得名。",
    "symbol": "沒有赤道",
    "currency": "中非法郎（XAF）",
    "language": "西班牙語 法語 葡萄牙語",
    "flag": "República_de_Guinea_Ecuatorial_FLAG.png",
    "emblem": "República_de_Guinea_Ecuatorial_EMBLEM.png",
    "headOfState": "總統：特奧多羅·奧比昂·恩圭馬·姆巴索戈Teodoro Obiang Nguema Mbasogo 總理：伊格納西奧·米拉姆·坦恩Ignacio Milam Tang",
    "politics": "總統制共和國",
    "atmosphere": "赤道幾內亞位於赤道地區，氣候濕熱，平均溫度為25度，相對濕度98％。降雨部分，畢歐科島年降雨量為1903豪米，年降雨日約128天；孟尼河區乾雨季分明，每年5月至9月為乾季，其餘時間為雨季，年降雨量為1714豪米，年降雨日約113天",
    "geography": "赤道幾內亞，包含兩大部分，一部分稱為木尼河地區，位於非洲大陸，大致呈東西長、南北窄的長方形，與喀麥隆、加彭接壤，木尼河斜貫該地區。該區以巴塔為主要都市。二是位於木尼河區西北、幾內亞灣中的比奧科島，此外在比奧科島西南595公里處還有安諾本島（Annobón）。",
    "capital": "馬拉博 Malabo",
    "population": "0.7 Million",
    "faith": [{
        "name": "天主教",
        "percentage": 88.7
      }, {
        "name": "其他",
        "percentage": 12.3
      }
    ],
    "economy": "主要：石油、可可、咖啡 次要：農業、漁產品加工、旅遊和金融服務業"
  },
  {
    "iso": "LBY",
    "country": "利比亞",
    "introduction": "是北非的一個國家，位於地中海南岸，與埃及、蘇丹、查德、尼日、阿爾及利亞跟突尼西亞相鄰；曾先後屬於羅馬帝國、阿拉伯帝國及鄂圖曼帝國；利比亞內戰後組建的新政府又改國號為「利比亞國」。",
    "symbol": "塞卜拉泰古城 石油",
    "currency": "利比亞第納爾（Dinar）",
    "language": "阿拉伯語",
    "flag": "State_of_Libya_FLAG.png",
    "emblem": "State_of_Libya_emblem.png",
    "headOfState": "國家元首（國民代表大會主席）：阿基拉·薩拉赫·伊薩 政府首腦（總理）：阿卜杜拉·薩尼",
    "politics": "共和立憲制 地方分權制",
    "atmosphere": "利比亞沿海地區屬地中海型氣候，內陸廣大地區屬熱帶沙漠氣候，年均溫為20度，夏季常有乾旱情況發生，每年6月至10月有沙漠風暴，溫度可達44度；首都1月份平均溫度為8度至16度，7月溫度為22至29度",
    "geography": "地處北非，北瀕地中海，海岸線長1,900多公里，東與埃及，西與阿爾及利亞、突尼西亞為鄰，南接尼日及查德。利國人民大多居住於北部沿海狹長的平原上。 利比亞除北部沿海地區有狹長的平原及南部山區外，大部分均為沙漠，占總面積的94%。大部分地區海拔300-600米。",
    "capital": "黎波里 Tripoli",
    "population": "6 Million",
    "faith": [{
        "name": "伊斯蘭教",
        "percentage": 92.7
      }, {
        "name": "基督宗教",
        "percentage": 4.0
      }, {
        "name": "其他",
        "percentage": 4.3
      }
    ],
    "economy": "石油、鋼鐵、石油加工、電力、紡織、食品加工"
  },
  {
    "iso": "SOM",
    "country": "索馬利亞",
    "introduction": "該國為東非國家，由於索馬利亞內戰連連，制度低下，當地人民部分以海盜為業，亞丁灣為其主要出沒海域。",
    "symbol": "海盜",
    "currency": "索馬利亞先令（SOS",
    "language": "索馬利亞語、阿拉伯語、英語、義大利語",
    "flag": "Somalia_Flag.png",
    "emblem": "Somalia_emblem.png",
    "headOfState": "總統：哈桑·謝赫·馬哈茂德",
    "politics": "議會民主制",
    "atmosphere": "大部屬於熱帶沙漠氣候，年降水量自南而北從500～600毫米減至100毫米以下，東北海岸偶爾會有來自北印度洋的氣旋風暴吹襲。",
    "geography": "索馬利亞全境以平緩的低高原為主，高度由北向南漸降。有沿海平原、內陸高原、北部山地等地形區。有謝貝利河和朱巴河。",
    "capital": "摩加迪休 Mogadishu",
    "population": "10 Million",
    "faith": [{
        "name": "伊斯蘭教",
        "percentage": 98
      }, {
        "name": "傳統信仰",
        "percentage": 2
      }
    ],
    "economy": "畜牧業、半農半牧"
  },
  {
    "iso": "MWI",
    "country": "馬拉威",
    "introduction": "馬拉威政局最穩定和少數沒有受內戰影響的非洲國家。然而，曾被聯合國評為世界上最不發達的國家之一，全國約有55%的人生活在貧窮線以下，人均國民生產總值只有600美元，是全世界最低收入的一群。",
    "symbol": "東非大裂谷",
    "currency": "馬拉威克瓦查（MWK）",
    "language": "齊切瓦語、英語",
    "flag": "Malawi_flag.png",
    "emblem": "Malawi_emblem.png",
    "headOfState": "總統：彼得·穆塔里卡",
    "politics": "總統制",
    "atmosphere": "大部份地區的氣候垂直差異顯著，為熱帶乾濕季氣候區的高地氣候，普遍來說高山平原的氣溫十分溫和和穩定，但冬天的氣溫可以低至攝氏4度。而盆地的氣溫較為悶熱，最熱的時候可以攝氏39度，而每年的降雨量也因地理環境而有所差別，平均由600mm至3000mm不等。通常雨季由11月開始至5月，而5月至11月的降雨量很低。馬拉威因處於高原地帶，所以極少受到颶風、洪水等威脅。",
    "geography": "馬拉威位於非洲東南部，南北有東非大裂谷貫穿，谷底就是馬拉威湖，是非洲第三大湖，占馬拉威總面積的20％。希雷河出自馬拉威湖南端，流經馬拉威南部地區，最後注入400公里以南的贊比西河。裂谷的東西面為海拔達900-1200米的高原。北部地區的尼卡高原高達2600米。南部的希雷高地平均海拔600－1600米，不過也有松巴高原高2130米，和木蘭吉山達3050米。希雷河下游地勢較低，海拔只有60－90米。",
    "capital": "里朗威Lilongwe",
    "population": "12 Million",
    "faith": [{
        "name": "天主教",
        "percentage": 79.9
      }, {
        "name": "回教",
        "percentage": 12.8
      }, {
        "name": "其他",
        "percentage": 3
      }, {
        "name": "沒有宗教信仰",
        "percentage": 4.3
      }
    ],
    "economy": "農業"
  },
  {
    "iso": "TUN",
    "country": "突尼西亞",
    "introduction": "迦太基的發源地和國家中樞。這個位於北非的國家統治了西班牙，北非，地中海沿岸等零星地區，成為當時地中海最強盛的國家，並因此成為以後羅馬的強敵，迦太基名將漢尼拔曾經一度要攻入羅馬的首都。後來北非第三次布匿戰爭後，迦太基被征服並成為羅馬共和國的阿非利加行省。",
    "symbol": "橄欖油",
    "currency": "突尼西亞第納爾（TDN）",
    "language": "阿拉伯語、法語",
    "flag": "Tunisia_flag.png",
    "emblem": "Tunisia_emblem.png",
    "headOfState": "總統：貝吉·凱德·埃塞卜西 總理：哈比卜·埃西德",
    "politics": "共和制",
    "atmosphere": "突尼西亞北部屬於夏乾冬雨的地中海型氣候，中部是熱帶草原氣候，南部屬熱帶沙漠氣候。",
    "geography": "國土面積的40%為撒哈拉沙漠所占據，餘下的60％則是十分富饒的土地。北部為高山與丘陵地，主要是亞特拉斯山脈東部的延伸；中部為階梯狀台地，由西向東傾斜，台地以南多季節性鹽沼；東部為狹長的沿海平原；南部則為撒哈拉沙漠。 ",
    "capital": "突尼斯Tunis",
    "population": "0.9 Million",
    "faith": [{
        "name": "伊斯蘭教",
        "percentage": 98
      }, {
        "name": "基督教",
        "percentage": 1
      }, {
        "name": "猶太教或其他宗教",
        "percentage": 1
      }
    ],
    "economy": "農業、觀光業"
  },
  {
    "iso": "CMR",
    "country": "喀麥隆",
    "introduction": "喀麥隆最早的居民是俾格米人的巴卡部落。說班圖語的族裔最早也起源於喀麥隆的高地地區，但在歐洲人入侵前，大部分已經遷走。到1884年為止，國王—杜阿拉（Douala）是喀麥隆當地最具有權力的來自非洲本土的君主。",
    "symbol": "克羅斯河大猩猩",
    "currency": "中非法郎（XAF）",
    "language": "法語、英語",
    "flag": "Cameroun_flag.png",
    "emblem": "Cameroun_EMBLEM.png",
    "headOfState": "總統：保羅·比亞 總理：菲利蒙·楊",
    "politics": "共和制",
    "atmosphere": "西南沿海有寬達150公里的低地，北部氣候燥熱，為熱帶草原氣候，自北向南，過度到熱帶雨林氣候，大部分地區年降水量1000-4000毫米，西南部火山區可達6000毫米以上。",
    "geography": "大部分為高原，一般海拔1000-1500米，中部地勢漸高，為高原地形。西部有一系列圓頂火山、丘陵，喀麥隆火山海拔4070米，為西非最高峰。",
    "capital": " 雅恩德Yaounde",
    "population": "1.5 Million",
    "faith": [{
        "name": "天主教",
        "percentage": 40
      }, {
        "name": "基督新教",
        "percentage": 30
      }, {
        "name": "伊斯蘭教",
        "percentage": 20
      }, {
        "name": "其他",
        "percentage": 10
      }
    ],
    "economy": "農業、漁業、畜牧業"
  },
  {
    "iso": "MOZ",
    "country": "莫三比克",
    "introduction": "與英國並無憲制關係的國家，在1995年以特殊例子加入大英國協；因其經濟低落再加上曾為社會主義國家，國內經濟等數值常被拿來與朝鮮比較。",
    "symbol": "奴隸貿易 象牙",
    "currency": "梅蒂卡爾(MZN)",
    "language": "葡萄牙語、Bantn、英語",
    "flag": "Mozambique_flag.png",
    "emblem": "Mozambique_Emblem.png",
    "headOfState": "總統：阿曼多·格布扎 總理：路易莎·迪奧戈",
    "politics": "共和制",
    "atmosphere": "南回歸線在南部通過，因此莫三比克的氣候，北部屬熱帶。南部是副熱帶，所以境內氣候炎熱潮濕，全年平均氣溫為攝氏19.4（華氏67度）。這個國家年分乾濕兩季，乾季比較短，為每年四月至八月；濕季很長，為每年九月到次年五月。因此雨水豐富，幾乎常年都會下雨，年雨量約500公釐到1000公釐。中部三比西河下游沿岸雨量最多，年雨量差不多有1000公釐到1500公釐。",
    "geography": "莫三比克地勢大致自西北向東南傾斜，贊比西河斜貫中部入海，河以北主要是高原，一般海拔500-1500米，沿岸平原較窄，以南主要是平原，最寬處約300公里，濱海多沼澤、沙洲和紅樹林。",
    "capital": "馬布多Maputo",
    "population": "1.8 Million",
    "faith": [{
        "name": "天主教",
        "percentage": 29
      }, {
        "name": "基督新教",
        "percentage": 16
      }, {
        "name": "伊斯蘭教",
        "percentage": 18
      }, {
        "name": "其他",
        "percentage": 37
      }
    ],
    "economy": "農業、漁業、畜牧業、工業、礦業"
  },
  {
    "iso": "MDG",
    "country": "馬達加斯加 République de Madagascar",
    "introduction": "長期與鄰近大陸隔離，馬達加斯加擁有的豐富動植物種類中有許多都是該國獨有，近90%是特有種。如狐猴、肉食性的馬島長尾狸貓和大量鳥類。一些生態學家因這種獨特的生態系統而將馬達加斯加稱為「第八大洲」，國際也將該島列為生物多樣性熱點地區。",
    "symbol": "變色龍、猴麵包樹、狐猴",
    "currency": "阿里阿里（Malagasy Ariary，MGA）",
    "language": "法語、馬拉加西語",
    "flag": "Madagascar_flag.png",
    "emblem": "Madagascar_seal.png",
    "headOfState": "總統：Hery Rajaonarimampianina 總理：Jean Ravelonarivo",
    "politics": "半總統共和制",
    "atmosphere": "受東南信風和西北季風的共同影響，馬達加斯加每年11月至次年4月都是炎熱的雨季，並且經常會遭遇破壞性的氣旋襲擊，每年的5至10月則是相對較為涼爽的旱季。源於印度洋上空的雨雲會在島上東部沿海地區上空釋放掉大部分濕氣，充沛的降水支撐當地雨林生態系統。中部高地相比東部來說較為乾燥和涼爽，西部則更為乾燥，島上的西南和南部內陸以半乾旱氣候為主。",
    "geography": "東海岸沿線存在一條狹長險峻的陡崖，這裡有著島上保留的大部分熱帶低地森林。陡崖所在山脊以西是位於島嶼中部的高原，海拔高度在750到1500米之間。這一中部高地以梯田為主，長滿草地的山地和丘陵之間的山谷中種有水稻，其間還穿插有曾一度覆蓋大片高原地區的半濕潤森林。高地以西地形逐漸乾燥，地勢向沿海地區的莫三比克海峽和紅樹林沼澤傾斜。",
    "capital": "安塔那那利佛Antananarivo",
    "population": "22.3 Million",
    "faith": [{
        "name": "伊斯蘭教",
        "percentage": 7
      }, {
        "name": "傳統宗教",
        "percentage": 50
      }, {
        "name": "基督宗教",
        "percentage": 40
      }, {
        "name": "其他",
        "percentage": 3
      }
    ],
    "economy": [{
        "name": "一級產業-農業",
        "percentage": 28.1
      }, {
        "name": "二級產業-製造業",
        "percentage": 17.4
      }, {
        "name": "三級產業-服務業",
        "percentage": 54.5
      }
    ]
  },
  {
    "iso": "CPV",
    "country": "維德角República de Cabo Verde",
    "introduction": "當葡萄牙人在1456年到達之前，維德角群島尚無人居住，之後，維德角群島成為葡萄牙的一部份。由於該群島位於非洲外海，維德角群島成了重要的港口，也成了重要的奴隸貿易中心。大部份維德角的居民都是白人殖民者與黑人奴隸混血的後裔。住在境外的維德角人人數比境內還多。",
    "symbol": "咖啡",
    "currency": "埃斯庫多（CVE）",
    "language": "葡萄牙語",
    "flag": "Cape_verde_flag.png",
    "emblem": "cape_verde_seal.png",
    "headOfState": "總統：Jorge Carlos de Almeida Fonseca 總理：José Maria Pereira Neves",
    "politics": "共和制",
    "atmosphere": "常年受副熱帶高壓及信風帶控制，西岸加那利寒流降溫降濕，形成熱帶沙漠氣候，全年氣溫維持在25攝氏度左右。維德角主要有兩個季節：雨季為8月到10月，旱季為12月到次年6月。降水不規律，易發生旱災。",
    "geography": "主要由10個島和8個小島組成，可分為兩部分：位於北部的向風群島和南部的背風群島。這些島嶼中，只有聖露西亞島是無人居住的島嶼，現在是一個自然保護區。所有這些島嶼都是火山島，福戈島上還有活火山。  ",
    "capital": "普亞拉 Praia",
    "population": "0.56 Million",
    "faith": [{
        "name": "天主教",
        "percentage": 78.7
      }, {
        "name": "基督宗教",
        "percentage": 10.4
      }, {
        "name": "其他",
        "percentage": 10.9
      }
    ],
    "economy": [{
        "name": "一級產業-農業",
        "percentage": 10
      }, {
        "name": "二級產業-工業",
        "percentage": 18.6
      }, {
        "name": "三級產業-服務業",
        "percentage": 71.4
      }
    ]
  },
  {
    "iso": "CAF",
    "country": "中非共和國République centrafricaine",
    "introduction": "中非原為販售黑奴的交通要道，1894年納入法屬剛果，1903年為法屬烏班基沙立領地（Territoire d'Oubangui-Chari），1910年屬法屬赤道非洲，1958年成立自治政府，之後成為半自治的中非共和國，至1960年獨立。目前國內陷入穆斯林與基督徒的族群衝突而內戰不斷。",
    "symbol": "鑽石、棉花",
    "currency": "中非法郎（XAF）",
    "language": "法語",
    "flag": "republic_centrafrica_flag.png",
    "emblem": "republic_centrafrica_seal.png",
    "headOfState": "總統：Catherine Samba-Panza 總理：Mahamat Kamoun",
    "politics": "共和制",
    "atmosphere": "北部屬於熱帶莽原氣候，南部則為熱帶雨林氣候，平均氣溫約攝氏27.8度（華氏82度）。南部一帶，雨季長達八個月，雨水豐富，最南部年雨量約一千兩百毫米，河谷附近地帶，也很潮濕，適於農耕。",
    "geography": "位在非洲大陸的中心，距海約一千公里，是個沒有出海口的內陸國家。境內地勢高亢，丘陵起伏，平均海拔約七百公尺，是非洲中南部的高原地帶。",
    "capital": "班基 Bangui",
    "population": "4.4 Million",
    "faith": [{
        "name": "傳統宗教",
        "percentage": 60
      }, {
        "name": "天主教",
        "percentage": 20
      }, {
        "name": "基督教",
        "percentage": 15
      }, {
        "name": "伊斯蘭教",
        "percentage": 5
      }
    ],
    "economy": [{
        "name": "一級產業-農業",
        "percentage": 55.1
      }, {
        "name": "二級產業-工業",
        "percentage": 12.5
      }, {
        "name": "三級產業-服務業",
        "percentage": 32.4
      }
    ]
  },
  {
    "iso": "COM",
    "country": "葛摩 Comores",
    "introduction": "葛摩為馬達加斯加的周邊群島之一，南島語系民族，非洲大陸的班圖人、阿拉伯人和來自印度尼西亞的移民接踵而來，在此定居。在1841年至1912年間，為法國殖民地，1946年成為法國「海外領地」。",
    "symbol": "依蘭精油",
    "currency": "葛摩法郎（Comorian franc，KMF）",
    "language": "法語、阿拉伯語",
    "flag": "Comoros_flag.png",
    "emblem": "Comoros_seal.png",
    "headOfState": "總統：Ikililou Dhoinine",
    "politics": "聯邦制、共和制",
    "atmosphere": "熱帶氣候，5-10月涼爽乾燥，11月至次年4月炎熱潮濕。年降水量1000-3000毫米。",
    "geography": "葛摩群島由四個主要島嶼組成，位於印度洋，在非洲海岸和馬達加斯加之間。群島上有數座或低矮或峻峭的火山，多為死火山，唯一大葛摩島上的高達2316米（7598英尺）的卡爾塔拉山（Le Karthala）是一座活火山。多森林。",
    "capital": "莫洛尼 Moroni",
    "population": "0.79 Million",
    "faith": [{
        "name": "伊斯蘭教",
        "percentage": 98
      }, {
        "name": "基督宗教",
        "percentage": 2
      }
    ],
    "economy": [{
        "name": "一級產業-農業",
        "percentage": 50.4
      }, {
        "name": "二級產業-工業",
        "percentage": 13.7
      }, {
        "name": "三級產業-服務業",
        "percentage": 35.9
      }
    ]
  },
  {
    "iso": "GNB",
    "country": "幾內亞比索 República da Guiné-Bissau",
    "introduction": "幾內亞比索曾被葡萄牙殖民地達四百年之久，十七至十九世紀間，葡萄牙人將幾畢做為奴隸交易的大本營，至今這裏仍是一片赤貧與屬靈黑暗之區。此外，在葡萄牙統治期間，天主教與政府合作密切，基督教則被禁止，一九七四年獨立後對基督教的限制才逐漸放寬。",
    "symbol": "腰果、Gunbe",
    "currency": "西非法郎（XOF）",
    "language": "葡萄牙語",
    "flag": "Guiné_Bissau_flag.gif",
    "emblem": "Guinea_Bissau_seal.png",
    "headOfState": "總統：José Mário Vaz 總理：Domingos Simões Pereira",
    "politics": "共和制",
    "atmosphere": "幾內亞比索屬熱帶海洋性季風氣候，通常炎熱潮濕。6月到11月是季風型雨季，吹西南風。12月到5月是旱季，吹東北哈馬丹風（harmattan）。",
    "geography": "位於非洲西部，包括比熱戈斯群島等島嶼。最高點約300米，境內東部為熱帶稀樹草原，地勢較高，大部分地區則為海岸平原。",
    "capital": "比索 Bissau",
    "population": "1.7 Million",
    "faith": [{
        "name": "傳統宗教",
        "percentage": 50
      }, {
        "name": "伊斯蘭教",
        "percentage": 45
      }, {
        "name": "基督宗教（多天主教）",
        "percentage": 5
      }
    ],
    "economy": [{
        "name": "一級產業-農業",
        "percentage": 50.4
      }, {
        "name": "二級產業-工業",
        "percentage": 13.7
      }, {
        "name": "三級產業-服務業",
        "percentage": 35.9
      }
    ]
  },
  {
    "iso": "SWZ",
    "country": "史瓦濟蘭 Kingdom of Swaziland",
    "introduction": "至今仍施行君主制，雖然國內居民屢次振呼改革，王室在該國還有相當重要地位。北、西、南三面為南非共和國所包圍，東北面與莫三比克為鄰，經濟多仰賴與南非的連結。由於英語讀音相近，人們常把它與瑞士（Switzerland）混淆，使它陰差陽錯而獲「非洲瑞士」之名。",
    "symbol": "鬥士盾牌",
    "currency": "里蘭吉尼（Swazi lilangeni，SZL）",
    "language": "英語、斯威士語、祖魯語",
    "flag": "Swaziland_flag.png",
    "emblem": "Swaziland_seal.png",
    "headOfState": "國王：Mswati III 首相：Sibusiso Dlamini",
    "politics": "君主立憲制",
    "atmosphere": "氣候屬南半球亞熱帶型，年雨量約900公釐，每年9月至翌年3月為雨季，雷電頻繁；高地年平均溫約攝氏16度，低地約23度，日夜溫差大。 ",
    "geography": "地勢西高東低，由於地勢平均較高，使得史瓦濟蘭成為非洲南部水源供應的主要地區。境內有四條主要河流由東部流經再注入印度洋，河川終年不竭。",
    "capital": "皇室首都：洛班巴Lobamba 行政首都：姆巴巴內Mbabane ",
    "population": "1.2 Million",
    "faith": [{
        "name": "基督教",
        "percentage": 40
      }, {
        "name": "天主教",
        "percentage": 20
      }, {
        "name": "伊斯蘭教",
        "percentage": 0.95
      }, {
        "name": "巴哈伊教",
        "percentage": 0.5
      }, {
        "name": "印度教",
        "percentage": 0.15
      }, {
        "name": "其他",
        "percentage": 38.4
      }
    ],
    "economy": [{
        "name": "一級產業-農業",
        "percentage": 7.2
      }, {
        "name": "二級產業-工業",
        "percentage": 47.4
      }, {
        "name": "三級產業-服務業",
        "percentage": 45.4
      }
    ]
  },
  {
    "iso": "ZMB",
    "country": "尚比亞 Republic of Zambia",
    "introduction": "尚比亞以銅礦為支柱產業。但由於國際市場銅礦價格下降和缺少投資等因素，銅產量逐年下降，1998年降到30年來最低點。2001年政府實行銅產業私有化後，銅礦開始回升，加上近年國際銅價，帶動銅礦業收入增加。尚比亞經濟復甦。2008年尚比亞人均收入已超過一千美元，脫離世界最貧困國家行列。",
    "symbol": "銅製品",
    "currency": "克瓦查（ZMK）",
    "language": "英語",
    "flag": "Zambija_flag.jpg",
    "emblem": "Zambia_seal.png",
    "headOfState": "總統：Edgar Lungu",
    "politics": "總統制",
    "atmosphere": "全境基本屬於熱帶草原氣候，年降水量600－1500毫米，每年10月到次年4月為雨季。",
    "geography": "尚比亞是一個內陸國家，大部份土地處于海拔1000－1500米的高原上，最高點海拔1774米，亦有丘陵和山地。  贊比西河是第一大河，橫貫南部邊境，有著名的莫西奧圖尼亞瀑布。",
    "capital": "路沙卡 Lusaka",
    "population": "14.1 Million",
    "faith": [{
        "name": "基督教",
        "percentage": 68
      }, {
        "name": "天主教",
        "percentage": 21
      }, {
        "name": "其他基督教派",
        "percentage": 9
      }, {
        "name": "其他",
        "percentage": 2
      }
    ],
    "economy": [{
        "name": "一級產業-農業",
        "percentage": 10.8
      }, {
        "name": "二級產業-工業",
        "percentage": 32.9
      }, {
        "name": "三級產業-服務業",
        "percentage": 56.3
      }
    ]
  },
  {
    "iso": "ZWE",
    "country": "辛巴威 Republic of Zimbabwe",
    "introduction": "辛巴威是南部非洲重要文明發源地，以大辛巴威古城為首都的穆胡姆塔巴帝國（Munhumutapa Empire）與回教商隊貿易，以象牙、黃金與銅礦等，換取波斯灣地區的布料與玻璃等生產品，15世紀時，已經成為非洲南部最大的邦國。 近年來該國因沒收歐裔土地而進行土地改革，接連受到西方國家的經濟制裁。政府大量印製新鈔來填補財政上的赤字，卻導致一蹶不振的經濟狀況。",
    "symbol": "大辛巴威（Great Zimbabwe）",
    "currency": "美元",
    "language": "英語",
    "flag": "Zimbabwe_flag.png",
    "emblem": "Zimbabwe_seal.png",
    "headOfState": "總統：Robert Gabriel Mugabe 總理：Morgan Richard Tsvangirai",
    "politics": "半總統制",
    "atmosphere": "辛巴威氣候屬於熱帶草原氣候，年均氣溫攝氏22度，10月份溫度最高，達32度，7月份溫度最低，約13～17度。",
    "geography": "辛巴威大部分地區是高原地形，平均海拔1000餘米。地形分高草原、中草原和低草原3種。辛巴威東部伊尼揚加尼山海拔2,592米，為全國最高點。主要河流有讚比西河和林波波河，分別是與鄰國尚比亞和南非的界河。維多利亞瀑布、三比西河、三比西河上游的卡里巴水壩與大壩攔阻河水積蓄而成的卡里巴湖共同圍成辛巴威北邊的疆界，與尚比亞相鄰。辛巴威的東邊國界全部與莫三比克相鄰，西南為波札那，南境則有一部分與南非相連，以林波波河為界。",
    "capital": "哈拉雷 Harare",
    "population": "13.7 Million",
    "faith": [{
        "name": "基督教",
        "percentage": 58
      }, {
        "name": "傳統宗教",
        "percentage": 40
      }, {
        "name": "伊斯蘭教",
        "percentage": 1
      }, {
        "name": "其他",
        "percentage": 1
      }
    ],
    "economy": [{
        "name": "一級產業-農業",
        "percentage": 20.1
      }, {
        "name": "二級產業-工業",
        "percentage": 25.7
      }, {
        "name": "三級產業-服務業",
        "percentage": 54.2
      }
    ]
  },
  {
    "iso": "ESH",
    "country": "撒拉威阿拉伯民主共和國 The Sahrawi Arab Democratic Republic",
    "introduction": "俗稱西撒哈拉，此處最為世人所知的是首都阿恩尤，已故作家三毛曾居住在此。從過去到現在，西撒哈拉與摩洛哥的領土爭議始終是雙方政治與治安的不穩主因。當地歌曲政治色彩濃厚，目的在於傳遞真相給每一代的西撒哈拉人，記取往日之痛。",
    "symbol": "撒哈拉沙漠",
    "currency": "薩拉威比薩塔 阿爾及利亞第納爾 DZD",
    "language": "阿拉伯語、西班牙語",
    "flag": "The_Sahrawi_Arab_Democratic_Republic_Flag.png",
    "emblem": "The_Sahrawi_Arab_Democratic_Republic_emblem.jpg",
    "headOfState": "總統：Mohamed Abdelaziz 總理：Abdelkader Taleb Omar",
    "politics": "總統制",
    "atmosphere": "熱帶沙漠氣候。白天涼爽因為來自大西洋的海風吹往內陸。夏季酷熱又漫長，最高可達攝氏五十度，冬季時在部分地區氣溫會降至攝氏七度左右。然而這裡的天氣終年都是萬里無雲的豔陽天。",
    "geography": "大片荒蕪沙漠，多沙多石，在南方及東北方有低矮群山。",
    "capital": "阿尤恩 El Aaiun",
    "population": "0.64 Million",
    "faith": [{
        "name": "伊斯蘭教",
        "percentage": 100
      }
    ],
    "economy": "服務業"
  },
  {
    "iso": "NER",
    "country": "尼日 Niger",
    "introduction": "尼日位於非洲中西部，撒哈拉沙漠南緣的內陸國。農業是主要的經濟命脈，再者基礎建設與經商條件較差，難以發展經濟及吸引外資。然而，2008年在中方協助下，境內發掘石油，自此之後尼日成為眾產油國之一。",
    "symbol": "戴伯斯長頸鹿石頭壁畫、Dabous Giraffes rock、art",
    "currency": "西非法郎",
    "language": "法語、豪薩語",
    "flag": "niger_flag.png",
    "emblem": "niger_emblem.png",
    "headOfState": "總統：Mahamadou Issoufou 總理：Brigi Rafini",
    "politics": "總統制",
    "atmosphere": "終年炎熱少雨，自然條件惡劣，平均氣溫攝氏三十度，最高可達五十度。雨季為六月到九月，旱季為十月到隔年五月。",
    "geography": "全境地勢北高南低，北部有高原及群山環繞，中部為半沙漠草原區，南部為平原。尼日河為其主要河流，其餘唯一些時令河。",
    "capital": "尼阿美 Niamey",
    "population": "19.93 Million",
    "faith": [{
        "name": "伊斯蘭教",
        "percentage": 80
      }, {
        "name": "傳統信仰與基督教",
        "percentage": 20
      }
    ],
    "economy": [{
        "name": "一級產業-農業",
        "percentage": 35
      }, {
        "name": "二級產業-工業",
        "percentage": 15
      }, {
        "name": "三級產業-服務業",
        "percentage": 50
      }
    ]
  }
]
